{
  "general" : {
    "FactionFriend"             : "http://fizzwidget.com/downloads/gfw-factionfriend-7-0-2.zip"
  },
  "curse" : {
    "Ace3"                      : "ace3",
    "ArkInventory"              : "ark-inventory",
    "AtlasLoot Enhanced"        : "atlasloot-enhanced",
    "Broker_Portal"             : "broker-portals",
    "Broker_RecountFu"          : "broker_recountfu",
    "Broker_SysMon"             : "broker_sysmon",
    "Chcolatebar"               : "chocolatebar",
    "DBM"                       : "deadly-boss-mods",
    "Dugi Questing Essential"   : "dugi-questing-essential",
    "Fizzle"                    : "fizzle",
    "GatherMate2"               : "gathermate2",
    "GatherMate2_Data"          : "gathermate2_data",
    "InFlight"                  : "inflight-taxi-timer",
    "Postal"                    : "postal",
    "MikScrollingBattleText"    : "mik-scrolling-battle-text",
    "Quartz"                    : "quartz",
    "RangeDisplay"              : "range-display",
    "Recount"                   : "recount",
    "TellMeWhen"                : "tellmewhen",
    "Vend-o-matic"              : "vendomatic",
    "Master Plan"               : "master-plan",
    "Garrison Mission Manager"  : "garrison-mission-manager",
    "WorldQuestsList"           : "world-quests-list",
    "ZPerl"                     : "zperl"
  }
}